pyekw/__init__.py
pyekw/constants.py
pyekw/courts.py
pyekw/courts_data.py
pyekw/generator.py
pyekw/utils.py
pyekw/validator.py
pyekw-0.2.0.dist-info/METADATA
pyekw-0.2.0.dist-info/WHEEL
pyekw-0.2.0.dist-info/licenses/LICENSE
pyekw-0.2.0.dist-info/RECORD
