Metadata-Version: 2.4
Name: pyekw
Version: 0.2.0
Summary: Python library for Polish eKW (Land Registry)
Project-URL: Homepage, https://github.com/mhajder/pyekw
Project-URL: Repository, https://github.com/mhajder/pyekw
Project-URL: Documentation, https://github.com/mhajder/pyekw#readme
Project-URL: Issues, https://github.com/mhajder/pyekw/issues
Author: Mateusz Hajder
License: MIT License
License-File: LICENSE
Keywords: ekw,land-registry,poland,utilities,validation
Classifier: Development Status :: 5 - Production/Stable
Classifier: Intended Audience :: Developers
Classifier: License :: OSI Approved :: MIT License
Classifier: Programming Language :: Python :: 3
Classifier: Programming Language :: Python :: 3.8
Classifier: Programming Language :: Python :: 3.9
Classifier: Programming Language :: Python :: 3.10
Classifier: Programming Language :: Python :: 3.11
Classifier: Programming Language :: Python :: 3.12
Classifier: Topic :: Software Development :: Libraries :: Python Modules
Classifier: Topic :: Utilities
Requires-Python: >=3.8
